lidipy/__init__.py
lidipy/container.py
lidipy/descriptors.py
lidipy/exceptions.py
lidipy/py.typed
lidipy/types.py
lidipy-0.3.2.dist-info/METADATA
lidipy-0.3.2.dist-info/WHEEL
lidipy-0.3.2.dist-info/licenses/LICENSE
lidipy-0.3.2.dist-info/RECORD
