Metadata-Version: 2.4
Name: lidipy
Version: 0.3.2
Summary: Lidi is a lightweight dependency injector designed to simplify dependency management in your Python projects.
License-File: LICENSE
Author: AlTosterino
Author-email: altosterino@gmail.com
Requires-Python: >=3.11
Classifier: Programming Language :: Python :: 3
Classifier: Programming Language :: Python :: 3.11
Classifier: Programming Language :: Python :: 3.12
Classifier: Programming Language :: Python :: 3.13
Classifier: Programming Language :: Python :: 3.14
